README.txt
setup.cfg
setup.py
docs/HISTORY.txt
docs/LICENSE.GPL
docs/LICENSE.txt
raptus/__init__.py
raptus.torii.egg-info/PKG-INFO
raptus.torii.egg-info/SOURCES.txt
raptus.torii.egg-info/dependency_links.txt
raptus.torii.egg-info/entry_points.txt
raptus.torii.egg-info/namespace_packages.txt
raptus.torii.egg-info/not-zip-safe
raptus.torii.egg-info/requires.txt
raptus.torii.egg-info/top_level.txt
raptus/torii/__init__.py
raptus/torii/carrier.py
raptus/torii/client.py
raptus/torii/component.xml
raptus/torii/config.py
raptus/torii/conversation.py
raptus/torii/datatypes.py
raptus/torii/interpreter.py
raptus/torii/python.py
raptus/torii/utilities.py
raptus/torii/scripts/pack.py