Metadata-Version: 1.0
Name: raptus.torii
Version: 1.0b2
Summary: Torii allows access to a running zope instance over a python prompt
Home-page: http://svn.plone.org/svn/collective/raptus.torii
Author: sriolo
Author-email: sriolo@raptus.com
License: GPL
Keywords: zope remote prompt zodb
Platform: UNKNOWN
Classifier: Framework :: Plone
Classifier: Framework :: Zope2
Classifier: Framework :: Zope3
Classifier: Framework :: ZODB
Classifier: Programming Language :: Python
